social_llama/__init__.py
social_llama/__main__.py
social_llama/config.py
social_llama/data_processing/dataclass.py
social_llama/data_processing/dataset_configs.py
social_llama/data_processing/social_dimensions.py
social_llama/math.py
social_llama/py.typed
social_llama/training/sft.py
social_llama/utils.py
social_llama-0.0.2.dist-info/entry_points.txt
social_llama-0.0.2.dist-info/WHEEL
social_llama-0.0.2.dist-info/LICENSE
social_llama-0.0.2.dist-info/METADATA
social_llama-0.0.2.dist-info/RECORD
