Metadata-Version: 2.1
Name: social-llama
Version: 0.0.2
Summary: Social Llama
Home-page: https://github.com/AGMoller/social-llama
License: MIT
Author: Anders Giovanni Møller
Author-email: andersgiovanni@gmail.com
Requires-Python: >=3.11.0,<3.12.0
Classifier: Development Status :: 1 - Planning
Classifier: License :: OSI Approved :: MIT License
Classifier: Programming Language :: Python :: 3
Classifier: Programming Language :: Python :: 3.11
Requires-Dist: accelerate (>=0.22.0,<0.23.0)
Requires-Dist: bitsandbytes (>=0.41.1,<0.42.0)
Requires-Dist: click (>=8.0.1)
Requires-Dist: datasets (>=2.14.4,<3.0.0)
Requires-Dist: peft (>=0.5.0,<0.6.0)
Requires-Dist: scipy (>=1.11.2,<2.0.0)
Requires-Dist: torch (>=2.0.1,<3.0.0)
Requires-Dist: transformers (>=4.32.1,<5.0.0)
Requires-Dist: trl (>=0.7.1,<0.8.0)
Project-URL: Changelog, https://github.com/AGMoller/social-llama/releases
Project-URL: Documentation, https://social-llama.readthedocs.io
Project-URL: Repository, https://github.com/AGMoller/social-llama
